LICENSE.pdf
LICENSE_SF-19-096_apprentice_GPL_3.0.pdf
README.md
setup.py
apprentice/GP.py
apprentice/__init__.py
apprentice/appset.py
apprentice/io.py
apprentice/monomial.py
apprentice/mpi4py_.py
apprentice/onb.py
apprentice/ortho.py
apprentice/polynomialapproximation.py
apprentice/rationalapproximation.py
apprentice/rationalapproximationONB.py
apprentice/rationalapproximationSIP.py
apprentice/rationalapproximationSIPONB.py
apprentice/rationalapproximationSLSQP.py
apprentice/scaler.py
apprentice/testData.py
apprentice/tools.py
apprentice/weights.py
apprenticeDFO.egg-info/PKG-INFO
apprenticeDFO.egg-info/SOURCES.txt
apprenticeDFO.egg-info/dependency_links.txt
apprenticeDFO.egg-info/requires.txt
apprenticeDFO.egg-info/top_level.txt
bin/app-build
bin/app-datadirtojson
bin/app-ls
bin/app-predict
bin/app-sample
bin/app-tune2
bin/app-yoda2h5
bin/app-yodaenvelope
etc/extrema.py
test/testONB.py