Metadata-Version: 2.1
Name: apprenticeDFO
Version: 1.1
Summary: The apprentice
Home-page: https://computing.fnal.gov/hep-on-hpc/
Author: Mohan Krishnamoorthy, Holger Schulz
Author-email: mkrishnamoorthy@anl.gov, iamholger@gmail.com
License: UNKNOWN
Platform: UNKNOWN
License-File: LICENSE.pdf
License-File: LICENSE_SF-19-096_apprentice_GPL_3.0.pdf
